jobutil/__init__.py
jobutil/jobutil.py
atd_jobs_util_dev-0.0.4.dist-info/LICENSE
atd_jobs_util_dev-0.0.4.dist-info/METADATA
atd_jobs_util_dev-0.0.4.dist-info/WHEEL
atd_jobs_util_dev-0.0.4.dist-info/top_level.txt
atd_jobs_util_dev-0.0.4.dist-info/RECORD
